LICENSE
MANIFEST.in
README.rst
setup.cfg
setup.py
bin/giles
bin/github
bin/jira
giles/__init__.py
giles/utils.py
giles.egg-info/PKG-INFO
giles.egg-info/SOURCES.txt
giles.egg-info/dependency_links.txt
giles.egg-info/requires.txt
giles.egg-info/top_level.txt
giles/commands/__init__.py
giles/commands/bases.py
giles/commands/giles/__init__.py
giles/commands/giles/subcommands/__init__.py
giles/commands/giles/subcommands/setup.py
giles/commands/github/__init__.py
giles/commands/github/subcommands/__init__.py
giles/commands/github/subcommands/branch.py
giles/commands/github/subcommands/list.py
giles/commands/github/subcommands/merge.py
giles/commands/github/subcommands/pull_request.py
giles/commands/github/subcommands/review.py
giles/commands/github/subcommands/submit.py
giles/commands/jira/__init__.py
giles/commands/jira/subcommands/__init__.py
giles/commands/jira/subcommands/assign.py
giles/commands/jira/subcommands/claim.py
giles/commands/jira/subcommands/comment.py
giles/commands/jira/subcommands/list.py
giles/commands/jira/subcommands/transition.py