Metadata-Version: 1.1
Name: giles
Version: 0.0.6
Summary: ``giles`` 
Home-page: https://github.com/anthonyalmarza/giles
Author: Anthony Almarza
Author-email: UNKNOWN
License: UNKNOWN
Keywords: giles,jira,workflow
Platform: UNKNOWN
Classifier: Intended Audience :: Developers
Classifier: Natural Language :: English
Classifier: Operating System :: OS Independent
Classifier: Programming Language :: Python
